refreshit/__init__.py
refreshit/refreshit.py
refreshit-0.2.dist-info/DESCRIPTION.rst
refreshit-0.2.dist-info/METADATA
refreshit-0.2.dist-info/RECORD
refreshit-0.2.dist-info/WHEEL
refreshit-0.2.dist-info/metadata.json
refreshit-0.2.dist-info/top_level.txt
